DesktopTools/__init__.py
DesktopTools/app/msg_systray.py
DesktopTools/args.py
DesktopTools/feather_hotkey/clip_string.py
DesktopTools/feather_hotkey/custom_list_widget.py
DesktopTools/feather_hotkey/models.py
DesktopTools/feather_hotkey/searchbar.ui
DesktopTools/feather_hotkey/searchbar_ui.py
DesktopTools/feather_hotkey/thread.py
DesktopTools/feather_hotkey/ui_searchbar.py
DesktopTools/feather_hotkey/win_searchbar.py
DesktopTools/feather_timer/data_alchemy/inputs.py
DesktopTools/feather_timer/data_alchemy/models.py
DesktopTools/feather_timer/data_alchemy/worktimes.py
DesktopTools/feather_timer/halahayawa.py
DesktopTools/feather_timer/input_counter.py
DesktopTools/feather_timer/monitor.py
DesktopTools/harry_potter.ico
DesktopTools/harry_potter.png
DesktopTools/logger.py
DesktopTools/main.py
DesktopTools/tools.py
DesktopTools/windows_main.py
desktoptools-0.1.5.dist-info/LICENSE
desktoptools-0.1.5.dist-info/METADATA
desktoptools-0.1.5.dist-info/WHEEL
desktoptools-0.1.5.dist-info/entry_points.txt
desktoptools-0.1.5.dist-info/RECORD
