Metadata-Version: 2.1
Name: DesktopTools
Version: 0.1.5
Summary: A desktop tool that includes some useful scripts.
Home-page: https://github.com/IanVzs/Halahayawa
License: MIT
Author: ianvzs
Author-email: ianvzs@outlook.com
Requires-Python: >=3.9,<4.0
Classifier: License :: OSI Approved :: MIT License
Classifier: Programming Language :: Python :: 3
Classifier: Programming Language :: Python :: 3.9
Classifier: Programming Language :: Python :: 3.10
Classifier: Programming Language :: Python :: 3.11
Classifier: Programming Language :: Python :: 3.12
Provides-Extra: ui
Requires-Dist: PySide6 (>=6.0.0,<7.0.0) ; (python_version >= "3.9" and python_version < "3.13") and (extra == "ui")
Requires-Dist: SQLAlchemy (>=2.0.0,<3.0.0)
Requires-Dist: loguru (>=0.6.0,<0.7.0)
Requires-Dist: psutil (>=5.9.4)
Requires-Dist: pydantic (>=1.10.7,<2.0.0)
Requires-Dist: pynput (>=1.7.6,<2.0.0)
Requires-Dist: requests (>=2.30.0)
Requires-Dist: wheel (>=0.40.0,<0.41.0)
Requires-Dist: yapf (>=0.32.0,<0.33.0)
Project-URL: Repository, https://github.com/IanVzs/Halahayawa
